surquest/utils/appstore_analytics_api/__init__.py
surquest/utils/appstoreconnect/analytics/__init__.py
surquest/utils/appstoreconnect/analytics/analytics.py
surquest/utils/appstoreconnect/analytics/client.py
surquest/utils/appstoreconnect/analytics/enums.py
surquest/utils/appstoreconnect/analytics/exceptions.py
surquest/utils/appstoreconnect/analytics/formatter.py
surquest_utils_appstoreconnect_analytics_api-0.0.1rc1.dist-info/METADATA
surquest_utils_appstoreconnect_analytics_api-0.0.1rc1.dist-info/WHEEL
surquest_utils_appstoreconnect_analytics_api-0.0.1rc1.dist-info/licenses/LICENSE
surquest_utils_appstoreconnect_analytics_api-0.0.1rc1.dist-info/RECORD
