Metadata-Version: 2.1
Name: surquest-utils-appstoreconnect-analytics-api
Version: 0.0.1rc1
Summary: Client library for AppStore Connect Analytics API 
Project-URL: Homepage, https://github.com/surquest/python-appstore-analytics-api
Project-URL: Bug Tracker, https://github.com/surquest/python-appstore-analytics-api/issues
Author-email: Michal Švarc <michal.svarc@surquest.com>
License-File: LICENSE
Requires-Dist: surquest-gcp-tracer~=0.1.0
Provides-Extra: test
Requires-Dist: pytest-cov>=4.0.0; extra == 'test'
Requires-Dist: pytest>=7.2.1; extra == 'test'
